README
setup.cfg
setup.py
gcudm/__init__.py
gcudm/base.py
gcudm/geometry.py
gcudm/meta.py
gcudm/model.py
gcudm/types.py
gcudm.egg-info/PKG-INFO
gcudm.egg-info/SOURCES.txt
gcudm.egg-info/dependency_links.txt
gcudm.egg-info/requires.txt
gcudm.egg-info/top_level.txt
gcudm/models/__init__.py
gcudm/models/esbems.py
gcudm/models/esbfire.py
gcudm/models/esblaw.py
gcudm/models/esbpsap.py
gcudm/models/esbs.py
gcudm/models/road_centerlines.py
gcudm/sphinx/__init__.py
gcudm/sphinx/ext/__init__.py
gcudm/sphinx/ext/modeldoc.py